pyolive/__init__.py
pyolive/__main__.py
pyolive/agent.py
pyolive/config.py
pyolive/develop.py
pyolive/heartbeat.py
pyolive/job_context.py
pyolive/job_executor.py
pyolive/log.py
pyolive/resource_watcher.py
pyolive/status.py
pyolive/utils.py
pyolive/channel/__init__.py
pyolive/channel/adapter.py
pyolive/channel/athena_client.py
pyolive/channel/consumer.py
pyolive/channel/producer.py
pyolive/db/__init__.py
pyolive/db/base.py
pyolive/db/factory.py
pyolive/db/mysql.py
pyolive/db/postgres.py
pyolive_ng-1.0.19.dist-info/licenses/LICENSE.txt
pyolive_ng-1.0.19.dist-info/METADATA
pyolive_ng-1.0.19.dist-info/WHEEL
pyolive_ng-1.0.19.dist-info/top_level.txt
pyolive_ng-1.0.19.dist-info/RECORD
