Metadata-Version: 2.4
Name: pyolive-ng
Version: 1.0.19
Summary: Python API for Athena pywok (Next Generation with Athena Broker).
Home-page: http://www.ingris.com
Author: Kiro Lee
Author-email: kiroly@ingris.com
License: Proprietary
Classifier: Development Status :: 4 - Beta
Classifier: Intended Audience :: Developers
Classifier: Programming Language :: Python :: 3
Classifier: Programming Language :: Python :: 3.12
Classifier: Programming Language :: Python :: 3.13
Requires-Python: >=3.12
License-File: LICENSE.txt
Requires-Dist: pynng>=0.8.0
Requires-Dist: PyYAML>=6.0.1
Requires-Dist: watchdog>=6.0.0
Requires-Dist: aiomysql>=0.2.0
Requires-Dist: asyncpg>=0.30.0
Dynamic: author
Dynamic: author-email
Dynamic: classifier
Dynamic: description
Dynamic: description-content-type
Dynamic: home-page
Dynamic: license
Dynamic: license-file
Dynamic: requires-dist
Dynamic: requires-python
Dynamic: summary
